LICENSE
README.md
pyproject.toml
setup.cfg
setup.py
async_anchio/__init__.py
async_anchio/api_client.py
async_anchio/api_response.py
async_anchio/configuration.py
async_anchio/exceptions.py
async_anchio/py.typed
async_anchio/rest.py
async_anchio/api/__init__.py
async_anchio/api/default_api.py
async_anchio/models/__init__.py
async_anchio/models/amount.py
async_anchio/models/anch_rest_api_utils_filters_contract_filter_schema_contractfilterschema_enum1.py
async_anchio/models/anch_rest_api_utils_filters_contract_filter_schema_contractfilterschema_enum2.py
async_anchio/models/anch_rest_api_utils_filters_employee_filter_schema_employeefilterschema_enum1.py
async_anchio/models/anch_rest_api_utils_filters_employee_filter_schema_employeefilterschema_enum2.py
async_anchio/models/anch_rest_api_utils_filters_tool_access_filter_schema_toolaccessfilterschema_enum1.py
async_anchio/models/anch_rest_api_utils_filters_tool_access_filter_schema_toolaccessfilterschema_enum2.py
async_anchio/models/api_key_context_input.py
async_anchio/models/api_key_context_output.py
async_anchio/models/api_key_provider.py
async_anchio/models/api_key_schema.py
async_anchio/models/api_key_schema_input.py
async_anchio/models/api_key_schema_output.py
async_anchio/models/bank_account_provider.py
async_anchio/models/bank_account_schema.py
async_anchio/models/change_password.py
async_anchio/models/checkout_session_request_schema.py
async_anchio/models/checkout_session_schema.py
async_anchio/models/company_role_schema.py
async_anchio/models/company_schema.py
async_anchio/models/company_schema_input.py
async_anchio/models/company_schema_output.py
async_anchio/models/company_sync_status.py
async_anchio/models/content_type_natural_key.py
async_anchio/models/contract_amount.py
async_anchio/models/contract_amount1.py
async_anchio/models/contract_schema.py
async_anchio/models/create_api_key_schema.py
async_anchio/models/default_schema.py
async_anchio/models/department_schema.py
python_async_anchio.egg-info/PKG-INFO
python_async_anchio.egg-info/SOURCES.txt
python_async_anchio.egg-info/dependency_links.txt
python_async_anchio.egg-info/requires.txt
python_async_anchio.egg-info/top_level.txt
